prefref/__init__.py
prefref/example1.py
prefref/example2.py
prefref/exceptions.py
prefref/prefref.py
prefref-25.5.600.dist-info/METADATA
prefref-25.5.600.dist-info/WHEEL
prefref-25.5.600.dist-info/licenses/LICENSE
prefref-25.5.600.dist-info/RECORD
